django_rest_gen/__init__.py
django_rest_gen/__main__.py
django_rest_gen/apigen.py
django_rest_gen/utils.py
django_rest_gen-0.1.2.dist-info/LICENSE
django_rest_gen-0.1.2.dist-info/METADATA
django_rest_gen-0.1.2.dist-info/WHEEL
django_rest_gen-0.1.2.dist-info/top_level.txt
django_rest_gen-0.1.2.dist-info/RECORD
