Metadata-Version: 2.1
Name: django-rest-gen
Version: 0.1.2
Summary: Rest API Code Generator
Author-email: Ahmad Alobaid <ahmad88me@gmail.com>
Project-URL: Homepage, https://github.com/ahmad88me/django-rest-gen
Project-URL: Bug Tracker, https://github.com/ahmad88me/django-rest-gen/issues
Classifier: Programming Language :: Python :: 3
Classifier: License :: OSI Approved :: MIT License
Classifier: Operating System :: OS Independent
Requires-Python: >=3.7
License-File: LICENSE
